scraply/__init__.py
scraply/cli.py
scraply/scraper.py
scraply-1.0.2.dist-info/METADATA
scraply-1.0.2.dist-info/WHEEL
scraply-1.0.2.dist-info/entry_points.txt
scraply-1.0.2.dist-info/top_level.txt
scraply-1.0.2.dist-info/RECORD
