Metadata-Version: 2.1
Name: scraply
Version: 1.0.2
Summary: A Python package to scrape and clone websites.
Home-page: https://github.com/ByteBreach/scraply
Author: Fidal
Author-email: mrfidal@proton.me
Classifier: Programming Language :: Python :: 3
Classifier: License :: OSI Approved :: MIT License
Classifier: Operating System :: OS Independent
Requires-Python: >=3.6
Requires-Dist: requests
Requires-Dist: beautifulsoup4
